README.rst
setup.cfg
setup.py
tf_reaper/__init__.py
tf_reaper/google_analytics.py
tf_reaper/loggers.py
tf_reaper/prompt.py
tf_reaper/reaper.py
tf_reaper/reaper_configuration.py
tf_reaper/reaper_filter.py
tf_reaper/reaper_statistics_reporter.py
tf_reaper.egg-info/PKG-INFO
tf_reaper.egg-info/SOURCES.txt
tf_reaper.egg-info/dependency_links.txt
tf_reaper.egg-info/entry_points.txt
tf_reaper.egg-info/requires.txt
tf_reaper.egg-info/top_level.txt