Metadata-Version: 1.1
Name: tf-reaper
Version: 0.1.3
Summary: Threshing Floor CLI utility for analyzing log files for noise.
Home-page: https://github.com/ThreshingFloor/cli.reaper.threshingfloor.io
Author: Threshing Floor Security, LLC
Author-email: info@threshingfloor.io
License: MIT
Platform: UNKNOWN
Classifier: Development Status :: 3 - Alpha
